{
  "action_counts": {
    "clv_shadow_watch": 15,
    "pass_or_monitor": 137,
    "price_unverified_watch": 17,
    "stale_started": 16
  },
  "artifacts": {
    "csv": "scored_consensus.csv",
    "html": "dashboard.html",
    "index": "index.html",
    "json": "summary.json",
    "markdown": "executive_summary.md"
  },
  "consensus_mtime": 1784588322.706594,
  "consensus_mtime_ns": 1784588322706594104,
  "consensus_path": "data/consensus/consensus_latest.csv",
  "consensus_rows": 185,
  "dashboard_version": "1784588322706594104:2026-07-20T18:58:48",
  "generated_at": "2026-07-20T18:58:48",
  "high_score_clv_unconfirmed_count": 0,
  "notes": [
    "This is a shadow decision surface, not production pick generation.",
    "Use only rows that are not started and whose current market price still matches or beats the listed entry.",
    "Public static mode only polls prebuilt summary.json and never recomputes from visitor requests."
  ],
  "prior_positive_clv_prob": 0.3126,
  "public_refresh_seconds": 60,
  "public_static": true,
  "refresh_command": "venv/bin/python scripts/render_expected_clv_consensus_dashboard.py --consensus data/consensus/consensus_latest.csv --training-end-date 2026-06-29 --public-static",
  "smoothing": 20.0,
  "target_date": "2026-07-20",
  "threshold": 0.36,
  "top_candidates": [
    {
      "action": "Shadow watch: candidate only if current price still beats or matches listed entry.",
      "action_label": "clv_shadow_watch",
      "consensus_score": 4.1,
      "data_quality_flags": "ok",
      "diagnostic_reason": "CLV gate cleared; live price check required",
      "edge_vs_threshold": 0.0089,
      "entry_odds": -110,
      "entry_odds_source": "explicit_american",
      "event_age_minutes": "",
      "event_date_et": "2026-07-20",
      "event_datetime_et": "",
      "event_status": "",
      "event_time_et": "19:07",
      "expected_positive_clv_prob": 0.3689,
      "game": "Tampa Bay Rays @ Toronto Blue Jays",
      "handicappers": "MrBigBets, BeezoWins, PatsPicks",
      "has_lock": "No",
      "league": "MLB",
      "market": "Total",
      "market_family": "total",
      "matched_feature_groups": 7,
      "matched_training_rows": 326,
      "minutes_to_event": "",
      "model_score_band": "score_under_6",
      "notes": "Odds: -110",
      "opposing_count": "0",
      "pick": "Under 7.5",
      "primary_capper": "MrBigBets",
      "prior_positive_clv_prob": 0.3126,
      "rank": 1,
      "row_key": "MLB|Tampa Bay Rays @ Toronto Blue Jays|Total|Under 7.5|19:07|MrBigBets, BeezoWins, PatsPicks",
      "source_count": "3",
      "source_count_bucket": "sources_3",
      "started": "No",
      "suggested_units": "1.5",
      "suggested_units_bucket": "units_1_to_1_99",
      "support_status": "strong_support",
      "threshold": 0.36
    },
    {
      "action": "Shadow watch: candidate only if current price still beats or matches listed entry.",
      "action_label": "clv_shadow_watch",
      "consensus_score": 4.3,
      "data_quality_flags": "ok",
      "diagnostic_reason": "CLV gate cleared; live price check required",
      "edge_vs_threshold": 0.007,
      "entry_odds": -110,
      "entry_odds_source": "explicit_american",
      "event_age_minutes": "",
      "event_date_et": "2026-07-20",
      "event_datetime_et": "",
      "event_status": "",
      "event_time_et": "19:15",
      "expected_positive_clv_prob": 0.367,
      "game": "San Diego Padres @ Atlanta Braves",
      "handicappers": "AndersPicks, TPD",
      "has_lock": "No",
      "league": "MLB",
      "market": "Total",
      "market_family": "total",
      "matched_feature_groups": 7,
      "matched_training_rows": 413,
      "minutes_to_event": "",
      "model_score_band": "score_under_6",
      "notes": "Odds: -110",
      "opposing_count": "0",
      "pick": "Over 9",
      "primary_capper": "AndersPicks",
      "prior_positive_clv_prob": 0.3126,
      "rank": 2,
      "row_key": "MLB|San Diego Padres @ Atlanta Braves|Total|Over 9|19:15|AndersPicks, TPD",
      "source_count": "2",
      "source_count_bucket": "sources_2",
      "started": "No",
      "suggested_units": "1.0",
      "suggested_units_bucket": "units_1_to_1_99",
      "support_status": "strong_support",
      "threshold": 0.36
    },
    {
      "action": "Shadow watch: candidate only if current price still beats or matches listed entry.",
      "action_label": "clv_shadow_watch",
      "consensus_score": 4.5,
      "data_quality_flags": "ok",
      "diagnostic_reason": "CLV gate cleared; live price check required",
      "edge_vs_threshold": 0.0043,
      "entry_odds": -110,
      "entry_odds_source": "explicit_american",
      "event_age_minutes": "",
      "event_date_et": "2026-07-20",
      "event_datetime_et": "",
      "event_status": "",
      "event_time_et": "21:40",
      "expected_positive_clv_prob": 0.3643,
      "game": "Cincinnati Reds @ Seattle Mariners",
      "handicappers": "Caruso, BeezoWins",
      "has_lock": "No",
      "league": "MLB",
      "market": "Total",
      "market_family": "total",
      "matched_feature_groups": 6,
      "matched_training_rows": 405,
      "minutes_to_event": "",
      "model_score_band": "score_under_6",
      "notes": "Odds: -110",
      "opposing_count": "0",
      "pick": "Under 7.5",
      "primary_capper": "Caruso",
      "prior_positive_clv_prob": 0.3126,
      "rank": 3,
      "row_key": "MLB|Cincinnati Reds @ Seattle Mariners|Total|Under 7.5|21:40|Caruso, BeezoWins",
      "source_count": "2",
      "source_count_bucket": "sources_2",
      "started": "No",
      "suggested_units": "1.5",
      "suggested_units_bucket": "units_1_to_1_99",
      "support_status": "strong_support",
      "threshold": 0.36
    },
    {
      "action": "Shadow watch: candidate only if current price still beats or matches listed entry.",
      "action_label": "clv_shadow_watch",
      "consensus_score": 4.1,
      "data_quality_flags": "ok",
      "diagnostic_reason": "CLV gate cleared; live price check required",
      "edge_vs_threshold": 0.0043,
      "entry_odds": 100,
      "entry_odds_source": "explicit_american",
      "event_age_minutes": "",
      "event_date_et": "2026-07-20",
      "event_datetime_et": "",
      "event_status": "",
      "event_time_et": "20:05",
      "expected_positive_clv_prob": 0.3643,
      "game": "Chicago White Sox @ Texas Rangers",
      "handicappers": "Caruso, BankrollBill",
      "has_lock": "No",
      "league": "MLB",
      "market": "Total",
      "market_family": "total",
      "matched_feature_groups": 6,
      "matched_training_rows": 405,
      "minutes_to_event": "",
      "model_score_band": "score_under_6",
      "notes": "Odds: +100",
      "opposing_count": "0",
      "pick": "Under 7.5",
      "primary_capper": "Caruso",
      "prior_positive_clv_prob": 0.3126,
      "rank": 4,
      "row_key": "MLB|Chicago White Sox @ Texas Rangers|Total|Under 7.5|20:05|Caruso, BankrollBill",
      "source_count": "2",
      "source_count_bucket": "sources_2",
      "started": "No",
      "suggested_units": "1.5",
      "suggested_units_bucket": "units_1_to_1_99",
      "support_status": "strong_support",
      "threshold": 0.36
    },
    {
      "action": "Shadow watch: candidate only if current price still beats or matches listed entry.",
      "action_label": "clv_shadow_watch",
      "consensus_score": 3.7,
      "data_quality_flags": "ok",
      "diagnostic_reason": "CLV gate cleared; live price check required",
      "edge_vs_threshold": 0.0043,
      "entry_odds": -105,
      "entry_odds_source": "explicit_american",
      "event_age_minutes": "",
      "event_date_et": "2026-07-20",
      "event_datetime_et": "",
      "event_status": "",
      "event_time_et": "19:40",
      "expected_positive_clv_prob": 0.3643,
      "game": "San Francisco Giants @ Kansas City Royals",
      "handicappers": "Mike's Research Bot 1.0, SmartMoneySports",
      "has_lock": "No",
      "league": "MLB",
      "market": "Total",
      "market_family": "total",
      "matched_feature_groups": 6,
      "matched_training_rows": 405,
      "minutes_to_event": "",
      "model_score_band": "score_under_6",
      "notes": "MLB; Odds: -105 to -115",
      "opposing_count": "0",
      "pick": "Over 10.5",
      "primary_capper": "Mike's Research Bot 1.0",
      "prior_positive_clv_prob": 0.3126,
      "rank": 5,
      "row_key": "MLB|San Francisco Giants @ Kansas City Royals|Total|Over 10.5|19:40|Mike's Research Bot 1.0, SmartMoneySports",
      "source_count": "2",
      "source_count_bucket": "sources_2",
      "started": "No",
      "suggested_units": "1.5",
      "suggested_units_bucket": "units_1_to_1_99",
      "support_status": "strong_support",
      "threshold": 0.36
    },
    {
      "action": "Shadow watch: candidate only if current price still beats or matches listed entry.",
      "action_label": "clv_shadow_watch",
      "consensus_score": 4.8,
      "data_quality_flags": "ok",
      "diagnostic_reason": "CLV gate cleared; live price check required",
      "edge_vs_threshold": 0.0018,
      "entry_odds": -138,
      "entry_odds_source": "explicit_american",
      "event_age_minutes": "",
      "event_date_et": "2026-07-20",
      "event_datetime_et": "",
      "event_status": "",
      "event_time_et": "19:10",
      "expected_positive_clv_prob": 0.3618,
      "game": "Baltimore Orioles @ Boston Red Sox",
      "handicappers": "Caruso",
      "has_lock": "No",
      "league": "MLB",
      "market": "Prop",
      "market_family": "prop",
      "matched_feature_groups": 7,
      "matched_training_rows": 607,
      "minutes_to_event": "",
      "model_score_band": "score_under_6",
      "notes": "Odds: -138",
      "opposing_count": "0",
      "pick": "Shane Baz Under 5.5 Strikeouts",
      "primary_capper": "Caruso",
      "prior_positive_clv_prob": 0.3126,
      "rank": 6,
      "row_key": "MLB|Baltimore Orioles @ Boston Red Sox|Prop|Shane Baz Under 5.5 Strikeouts|19:10|Caruso",
      "source_count": "1",
      "source_count_bucket": "sources_1",
      "started": "No",
      "suggested_units": "0.5",
      "suggested_units_bucket": "units_under_1",
      "support_status": "strong_support",
      "threshold": 0.36
    },
    {
      "action": "Shadow watch: candidate only if current price still beats or matches listed entry.",
      "action_label": "clv_shadow_watch",
      "consensus_score": 4.8,
      "data_quality_flags": "ok",
      "diagnostic_reason": "CLV gate cleared; live price check required",
      "edge_vs_threshold": 0.0018,
      "entry_odds": 118,
      "entry_odds_source": "explicit_american",
      "event_age_minutes": "",
      "event_date_et": "2026-07-20",
      "event_datetime_et": "",
      "event_status": "",
      "event_time_et": "19:40",
      "expected_positive_clv_prob": 0.3618,
      "game": "San Francisco Giants @ Kansas City Royals",
      "handicappers": "Caruso",
      "has_lock": "No",
      "league": "MLB",
      "market": "Prop",
      "market_family": "prop",
      "matched_feature_groups": 7,
      "matched_training_rows": 607,
      "minutes_to_event": "",
      "model_score_band": "score_under_6",
      "notes": "Odds: +118",
      "opposing_count": "0",
      "pick": "Trevor McDonald Over 3.5 Strikeouts",
      "primary_capper": "Caruso",
      "prior_positive_clv_prob": 0.3126,
      "rank": 7,
      "row_key": "MLB|San Francisco Giants @ Kansas City Royals|Prop|Trevor McDonald Over 3.5 Strikeouts|19:40|Caruso",
      "source_count": "1",
      "source_count_bucket": "sources_1",
      "started": "No",
      "suggested_units": "0.5",
      "suggested_units_bucket": "units_under_1",
      "support_status": "strong_support",
      "threshold": 0.36
    },
    {
      "action": "Shadow watch: candidate only if current price still beats or matches listed entry.",
      "action_label": "clv_shadow_watch",
      "consensus_score": 4.8,
      "data_quality_flags": "ok",
      "diagnostic_reason": "CLV gate cleared; live price check required",
      "edge_vs_threshold": 0.0018,
      "entry_odds": -104,
      "entry_odds_source": "explicit_american",
      "event_age_minutes": "",
      "event_date_et": "2026-07-20",
      "event_datetime_et": "",
      "event_status": "",
      "event_time_et": "21:40",
      "expected_positive_clv_prob": 0.3618,
      "game": "Oakland Athletics @ Arizona Diamondbacks",
      "handicappers": "Caruso",
      "has_lock": "No",
      "league": "MLB",
      "market": "Prop",
      "market_family": "prop",
      "matched_feature_groups": 7,
      "matched_training_rows": 607,
      "minutes_to_event": "",
      "model_score_band": "score_under_6",
      "notes": "Odds: -104",
      "opposing_count": "0",
      "pick": "Jeffrey Springs Over 3.5 Strikeouts",
      "primary_capper": "Caruso",
      "prior_positive_clv_prob": 0.3126,
      "rank": 8,
      "row_key": "MLB|Oakland Athletics @ Arizona Diamondbacks|Prop|Jeffrey Springs Over 3.5 Strikeouts|21:40|Caruso",
      "source_count": "1",
      "source_count_bucket": "sources_1",
      "started": "No",
      "suggested_units": "0.5",
      "suggested_units_bucket": "units_under_1",
      "support_status": "strong_support",
      "threshold": 0.36
    },
    {
      "action": "Shadow watch: candidate only if current price still beats or matches listed entry.",
      "action_label": "clv_shadow_watch",
      "consensus_score": 4.8,
      "data_quality_flags": "ok",
      "diagnostic_reason": "CLV gate cleared; live price check required",
      "edge_vs_threshold": 0.0018,
      "entry_odds": -135,
      "entry_odds_source": "explicit_american",
      "event_age_minutes": "",
      "event_date_et": "2026-07-20",
      "event_datetime_et": "",
      "event_status": "",
      "event_time_et": "19:15",
      "expected_positive_clv_prob": 0.3618,
      "game": "San Diego Padres @ Atlanta Braves",
      "handicappers": "Caruso",
      "has_lock": "No",
      "league": "MLB",
      "market": "Prop",
      "market_family": "prop",
      "matched_feature_groups": 7,
      "matched_training_rows": 607,
      "minutes_to_event": "",
      "model_score_band": "score_under_6",
      "notes": "Odds: -135",
      "opposing_count": "0",
      "pick": "JP Sears Over 3.5 Strikeouts",
      "primary_capper": "Caruso",
      "prior_positive_clv_prob": 0.3126,
      "rank": 9,
      "row_key": "MLB|San Diego Padres @ Atlanta Braves|Prop|JP Sears Over 3.5 Strikeouts|19:15|Caruso",
      "source_count": "1",
      "source_count_bucket": "sources_1",
      "started": "No",
      "suggested_units": "0.5",
      "suggested_units_bucket": "units_under_1",
      "support_status": "strong_support",
      "threshold": 0.36
    },
    {
      "action": "Shadow watch: candidate only if current price still beats or matches listed entry.",
      "action_label": "clv_shadow_watch",
      "consensus_score": 4.8,
      "data_quality_flags": "ok",
      "diagnostic_reason": "CLV gate cleared; live price check required",
      "edge_vs_threshold": 0.0018,
      "entry_odds": -145,
      "entry_odds_source": "explicit_american",
      "event_age_minutes": "",
      "event_date_et": "2026-07-20",
      "event_datetime_et": "",
      "event_status": "",
      "event_time_et": "21:40",
      "expected_positive_clv_prob": 0.3618,
      "game": "Cincinnati Reds @ Seattle Mariners",
      "handicappers": "Caruso",
      "has_lock": "No",
      "league": "MLB",
      "market": "Prop",
      "market_family": "prop",
      "matched_feature_groups": 7,
      "matched_training_rows": 607,
      "minutes_to_event": "",
      "model_score_band": "score_under_6",
      "notes": "Odds: -145",
      "opposing_count": "0",
      "pick": "Andrew Abbott Over 4.5 Strikeouts",
      "primary_capper": "Caruso",
      "prior_positive_clv_prob": 0.3126,
      "rank": 10,
      "row_key": "MLB|Cincinnati Reds @ Seattle Mariners|Prop|Andrew Abbott Over 4.5 Strikeouts|21:40|Caruso",
      "source_count": "1",
      "source_count_bucket": "sources_1",
      "started": "No",
      "suggested_units": "0.5",
      "suggested_units_bucket": "units_under_1",
      "support_status": "strong_support",
      "threshold": 0.36
    },
    {
      "action": "Shadow watch: candidate only if current price still beats or matches listed entry.",
      "action_label": "clv_shadow_watch",
      "consensus_score": 4.8,
      "data_quality_flags": "ok",
      "diagnostic_reason": "CLV gate cleared; live price check required",
      "edge_vs_threshold": 0.0018,
      "entry_odds": -125,
      "entry_odds_source": "explicit_american",
      "event_age_minutes": "",
      "event_date_et": "2026-07-20",
      "event_datetime_et": "",
      "event_status": "",
      "event_time_et": "19:15",
      "expected_positive_clv_prob": 0.3618,
      "game": "San Diego Padres @ Atlanta Braves",
      "handicappers": "Caruso",
      "has_lock": "No",
      "league": "MLB",
      "market": "Prop",
      "market_family": "prop",
      "matched_feature_groups": 7,
      "matched_training_rows": 607,
      "minutes_to_event": "",
      "model_score_band": "score_under_6",
      "notes": "Odds: -125",
      "opposing_count": "0",
      "pick": "Bryce Elder Over 3.5 Strikeouts",
      "primary_capper": "Caruso",
      "prior_positive_clv_prob": 0.3126,
      "rank": 11,
      "row_key": "MLB|San Diego Padres @ Atlanta Braves|Prop|Bryce Elder Over 3.5 Strikeouts|19:15|Caruso",
      "source_count": "1",
      "source_count_bucket": "sources_1",
      "started": "No",
      "suggested_units": "0.5",
      "suggested_units_bucket": "units_under_1",
      "support_status": "strong_support",
      "threshold": 0.36
    },
    {
      "action": "Shadow watch: candidate only if current price still beats or matches listed entry.",
      "action_label": "clv_shadow_watch",
      "consensus_score": 4.8,
      "data_quality_flags": "ok",
      "diagnostic_reason": "CLV gate cleared; live price check required",
      "edge_vs_threshold": 0.0018,
      "entry_odds": 115,
      "entry_odds_source": "explicit_american",
      "event_age_minutes": "",
      "event_date_et": "2026-07-20",
      "event_datetime_et": "",
      "event_status": "",
      "event_time_et": "19:40",
      "expected_positive_clv_prob": 0.3618,
      "game": "New York Mets @ Milwaukee Brewers",
      "handicappers": "Caruso",
      "has_lock": "No",
      "league": "MLB",
      "market": "Prop",
      "market_family": "prop",
      "matched_feature_groups": 7,
      "matched_training_rows": 607,
      "minutes_to_event": "",
      "model_score_band": "score_under_6",
      "notes": "Odds: +115",
      "opposing_count": "0",
      "pick": "Jacob Misiorowski Under 8.5 Strikeouts",
      "primary_capper": "Caruso",
      "prior_positive_clv_prob": 0.3126,
      "rank": 12,
      "row_key": "MLB|New York Mets @ Milwaukee Brewers|Prop|Jacob Misiorowski Under 8.5 Strikeouts|19:40|Caruso",
      "source_count": "1",
      "source_count_bucket": "sources_1",
      "started": "No",
      "suggested_units": "0.5",
      "suggested_units_bucket": "units_under_1",
      "support_status": "strong_support",
      "threshold": 0.36
    }
  ],
  "training_clv_rows": 419,
  "training_end_date": "2026-06-29",
  "walkforward_summary_path": "data/analysis/expected_clv_walkforward/2026-06-29/summary.json",
  "watch_candidate_count": 15
}
